rc_connectivity_check/.DS_Store
rc_connectivity_check/__init__.py
rc_connectivity_check/checker.py
rc_connectivity_check-0.1.8.dist-info/LICENSE
rc_connectivity_check-0.1.8.dist-info/METADATA
rc_connectivity_check-0.1.8.dist-info/WHEEL
rc_connectivity_check-0.1.8.dist-info/entry_points.txt
rc_connectivity_check-0.1.8.dist-info/RECORD
