Metadata-Version: 2.1
Name: rc-connectivity-check
Version: 0.1.8
Summary: Tool to check connectivity to RevenueCat services
License: MIT
Author: Guillermo Perez
Author-email: bisho@revenuecat.com
Requires-Python: >=3.9,<4.0
Classifier: License :: OSI Approved :: MIT License
Classifier: Programming Language :: Python :: 3
Classifier: Programming Language :: Python :: 3.9
Classifier: Programming Language :: Python :: 3.10
Classifier: Programming Language :: Python :: 3.11
Classifier: Programming Language :: Python :: 3.12
Classifier: Programming Language :: Python :: 3.13
Requires-Dist: colorama (>=0.4.6,<0.5.0)
Requires-Dist: requests (>=2.32.3,<3.0.0)
